npy4chan
