Metadata-Version: 1.1
Name: npy4chan
Version: 0.1.2.1
Summary: A trivial, minimalistic 4chan API wrapper.
Home-page: https://github.com/MineRobber9000/npy4chan
Author: Robert Miles
Author-email: milesrobert374@gmail.com
License: MIT
Keywords: 4chan imageboard API
Platform: UNKNOWN
Classifier: Development Status :: 3 - Alpha
Classifier: Intended Audience :: Developers
Classifier: Topic :: Internet :: WWW/HTTP
Classifier: Topic :: Internet :: WWW/HTTP :: Dynamic Content
Classifier: License :: OSI Approved :: MIT License
Classifier: Programming Language :: Python :: 2
Classifier: Programming Language :: Python :: 2.7
